{
  "2iPPlESWN4NdIFQuYoaw": "12a_honey_blonde.webp",
  "3WfQZH42XiWSgaQIV23l": "frontal_24_inch.webp",
  "4TgJy804QNslgSjPQXzg": "full_frontal_20_inc_brown.webp",
  "4WsJw2kvsIH6My2ml080": "curly_wet_waves_26_inch.webp",
  "4hCdKih0VbhyeysqXfth": "7x6_closure_lace_20__inch.webp",
  "58QAJ5Wp7d2GQ4I7peYl": "bob_wig.webp",
  "5MPrWf4KLkBPJQTwQiPc": "premuim_wig_18_inch.webp",
  "5i7RVLJBoylSU9w8pbaz": "straight_24_inch.webp",
  "64955ImLjMDiZyUQ0DhH": "13x4-frontal_lace-22_inch.jpg",
  "8L0IsWuVxaNqKZ3EyeCL": "4x4_glueless_10inch_bob.webp",
  "8Lve8ztBEeL7SKhlBrGe": "bob_10_inch_straight.webp",
  "96vr67bB0JRPyWEu3xBp": "brazillian_wig.webp",
  "979veDSaYtsPrBcqqAMW": "fringe_bob_8_inch.webp",
  "9o4KszqQl4wjNiKTl3NH": "Gemini_Generated_Image_uasixquasixquasi.png",
  "9ym05jl98ndNLtE2U84w": "Gemini_Generated_Image_t3rcr3t3rcr3t3rc.png",
  "AZdaMxA7MSVpnMmNEEV7": "short_curly_wig.webp",
  "BJT4gKHX2F7BV6AFziti": "blonde_wig.webp",
  "BOwtqCa064wlaQBk6H4k": "frontal_12_grade_24_inch.webp",
  "D2Qi0GeGVpJtKabcp0dU": "Ruby13x4Colour4-AugustPicture1_080205fd-4853-4e22-b23c-082bc1c0045e.webp",
  "DIaqhtMUhM4ZNGHTLaKI": "premuim_straight_peruvian_wig_18_inch.webp",
  "Dv6jO7H2PTzWDeoMEOTG": "curls_24_inch.webp",
  "EivT53FJpS4bMMnPGsQF": "kinky_curly_24_inch.jpg",
  "FJs5cz6McueUDoO3cijS": "12a_honey_blonde.webp",
  "FpxIhiRpE988XqkOB3bo": "frontal_24_inch.webp",
  "GIgyLoVR2PAqhCFgyarT": "full_frontal_20_inc_brown.webp",
  "GSaKmZCPSwPg48D7NEIi": "curly_wet_waves_26_inch.webp",
  "GYteBuxAKdULCrmSKpkh": "7x6_closure_lace_20__inch.webp",
  "Gj7QuZFS2VjWbhtjJqQg": "bob_wig.webp",
  "GsZ7A4CW3LLJkYVWtU4d": "premuim_wig_18_inch.webp",
  "HH6gzQY5ON0afChdyFWj": "straight_24_inch.webp",
  "HHjd6z3TrXSMOpNkRkzO": "13x4-frontal_lace-22_inch.jpg",
  "HT49BvDGk4QvDUlh76Ma": "4x4_glueless_10inch_bob.webp",
  "HzXSUjQYeQxDQRpHizCJ": "bob_10_inch_straight.webp",
  "IwXZRG9nxpKAw54nsvEJ": "brazillian_wig.webp",
  "KzTu7XAZwU3VdilmWq3m": "fringe_bob_8_inch.webp",
  "L7uJqoFtp0UxyZ6B9eRN": "Gemini_Generated_Image_uasixquasixquasi.png",
  "LPldezsb5IuZ7tKvubGJ": "Gemini_Generated_Image_t3rcr3t3rcr3t3rc.png",
  "LhdLuwyZTPK3EJfcCOib": "short_curly_wig.webp",
  "OAWhQWzLj1y0Bx1ab94K": "blonde_wig.webp",
  "PJlj8rUo847pEgog0Evq": "frontal_12_grade_24_inch.webp",
  "Q7A7tKNQGhagVaod4741": "Ruby13x4Colour4-AugustPicture1_080205fd-4853-4e22-b23c-082bc1c0045e.webp",
  "Qfe8DtnTy7aR8Q7xX99O": "premuim_straight_peruvian_wig_18_inch.webp",
  "TC3fkHUZ171mZf9MHiAk": "curls_24_inch.webp",
  "Ug7kHKl1lONuAZvRj4y3": "kinky_curly_24_inch.jpg",
  "V35Med86MLBkva49HvDt": "12a_honey_blonde.webp",
  "VdlYwsig0irzJDfbJAZb": "frontal_24_inch.webp",
  "VzDdEQ9jbusLo9SeMQkd": "full_frontal_20_inc_brown.webp",
  "XH3mP5B5NQBGyN1SI6bg": "curly_wet_waves_26_inch.webp",
  "XnP5EtCLaUM5JHQDz9iS": "7x6_closure_lace_20__inch.webp",
  "XnzthCScNRSHdvkXjmCx": "bob_wig.webp",
  "YOKUIwhQU3t3UMBaxskb": "premuim_wig_18_inch.webp",
  "YTulc4CxquIHgGg0rKvO": "straight_24_inch.webp",
  "Yjwl00szOhLD7w8rsLpi": "13x4-frontal_lace-22_inch.jpg",
  "Ynd48DXewE3xb3KiiVMx": "4x4_glueless_10inch_bob.webp",
  "ZPxQl3MfrsQ02twE0Zdh": "bob_10_inch_straight.webp",
  "ZXupVxA4u78uFZiuKAjX": "brazillian_wig.webp",
  "a3A9ePE4FyTczzVp0Glv": "fringe_bob_8_inch.webp",
  "aYvA8SYpRYhm2xRlo16H": "Gemini_Generated_Image_uasixquasixquasi.png",
  "awSPLix2o40wNMNtZDuq": "Gemini_Generated_Image_t3rcr3t3rcr3t3rc.png",
  "b243tIVBTdYulb9YdMKM": "short_curly_wig.webp",
  "chfuu4AGJpJaZdoShZRU": "blonde_wig.webp",
  "d82IY1HEZDBC4DsnsziW": "frontal_12_grade_24_inch.webp",
  "eQx5WlQ2em81673XciFz": "Ruby13x4Colour4-AugustPicture1_080205fd-4853-4e22-b23c-082bc1c0045e.webp",
  "ecWAfiuUCylu58GHZdsd": "premuim_straight_peruvian_wig_18_inch.webp",
  "fa567lExdGy57IaHmUSl": "curls_24_inch.webp",
  "fx7oJrM5vwK68sY4coZ0": "kinky_curly_24_inch.jpg",
  "guNTEUOdBmoS9FmbGVca": "12a_honey_blonde.webp",
  "gucw7Okjaqluf7tKerJN": "frontal_24_inch.webp",
  "hHMYVZHOxo5dI3GikLjk": "full_frontal_20_inc_brown.webp",
  "hcbm8SyjrZZgou991xMt": "curly_wet_waves_26_inch.webp",
  "iijN3nGRS593xWz5YK7T": "7x6_closure_lace_20__inch.webp",
  "j6GMlWD5d6NxpXSJhh5p": "bob_wig.webp",
  "l7I9rCiC6lm30ZVzxRVs": "premuim_wig_18_inch.webp",
  "m9bDjq78vrwqJ9fOcySu": "straight_24_inch.webp",
  "mbklo2Q6FG6pjTOys7hc": "13x4-frontal_lace-22_inch.jpg",
  "ntoLVZ55zRjI4B4tmMzA": "4x4_glueless_10inch_bob.webp",
  "oFRUEkEOTi92U6B7VfyC": "bob_10_inch_straight.webp",
  "od5qLvKZmgYmE3Ysjq75": "brazillian_wig.webp",
  "pRNNnBBDAlTeSeHY1QNR": "fringe_bob_8_inch.webp",
  "twcnw7bvtkptep2qJaQM": "Gemini_Generated_Image_uasixquasixquasi.png",
  "uuWmumix790NxTS4gsLb": "Gemini_Generated_Image_t3rcr3t3rcr3t3rc.png",
  "uull45294DD0x9hPvEAM": "short_curly_wig.webp",
  "vVRVYn7NEKx3SHO2geEn": "blonde_wig.webp",
  "vdYJYbTpPbvWgPMwObXX": "frontal_12_grade_24_inch.webp",
  "wYZQs7JGmR7cctlt4SQ1": "Ruby13x4Colour4-AugustPicture1_080205fd-4853-4e22-b23c-082bc1c0045e.webp",
  "wdGIDZZkxIwGbf88fCke": "premuim_straight_peruvian_wig_18_inch.webp",
  "ww6Km4QuZ1qR1T6JyskI": "curls_24_inch.webp",
  "xJoxJBsi8VaHucTb9HpS": "kinky_curly_24_inch.jpg"
}